lit_mcp/__init__.py
lit_mcp/__main__.py
lit_mcp/prompts/__init__.py
lit_mcp/prompts/author_spotlight.py
lit_mcp/prompts/latest_info.py
lit_mcp/prompts/related_topics.py
lit_mcp/utils/__init__.py
lit_mcp/utils/arxiv.py
lit_mcp/utils/dblp.py
lit_mcp-1.0.0.dist-info/METADATA
lit_mcp-1.0.0.dist-info/WHEEL
lit_mcp-1.0.0.dist-info/entry_points.txt
lit_mcp-1.0.0.dist-info/licenses/LICENSE
lit_mcp-1.0.0.dist-info/RECORD
