Metadata-Version: 2.4
Name: lit-mcp
Version: 1.0.0
Summary: A MCP server layer for existing APIs from popular sources e.g. arXiv, DBLP, etc. to help researchers expedite literature review process using LLMs and MCP Clients like Claude, Cursor, etc.
Project-URL: Homepage, https://github.com/gauravfs-14/lit-mcp
Project-URL: Repository, https://github.com/gauravfs-14/lit-mcp
Project-URL: Issues, https://github.com/gauravfs-14/lit-mcp/issues
Author-email: Gaurab Chhetri <contact@gaurabchhetri.com.np>
License: MIT
License-File: LICENSE
Keywords: academic,arxiv,dblp,literature,mcp,papers,research
Classifier: Development Status :: 4 - Beta
Classifier: Intended Audience :: Science/Research
Classifier: License :: OSI Approved :: MIT License
Classifier: Operating System :: OS Independent
Classifier: Programming Language :: Python :: 3
Classifier: Programming Language :: Python :: 3.12
Classifier: Topic :: Scientific/Engineering
Classifier: Topic :: Software Development :: Libraries :: Python Modules
Requires-Python: >=3.12
Requires-Dist: arxiv>=2.2.0
Requires-Dist: httpx>=0.28.1
Requires-Dist: mcp[cli]>=1.14.1
Requires-Dist: requests>=2.31.0
